tensor_annotations/__init__.py
tensor_annotations/axes.py
tensor_annotations/jax.py
tensor_annotations/jax.pyi
tensor_annotations/numpy.py
tensor_annotations/numpy.pyi
tensor_annotations/py.typed
tensor_annotations/tensorflow.py
tensor_annotations/tensorflow.pyi
tensor_annotations/library_stubs/third_party/py/numpy/__init__.pyi
tensor_annotations/tests/jax.py
tensor_annotations/tests/numpy.py
tensor_annotations/tests/pytype.py
tensor_annotations/tests/templates.py
tensor_annotations/tests/tensorflow.py
tensor_annotations/tests/utils.py
tensor_annotations-2.0.3.dist-info/LICENSE
tensor_annotations-2.0.3.dist-info/METADATA
tensor_annotations-2.0.3.dist-info/WHEEL
tensor_annotations-2.0.3.dist-info/top_level.txt
tensor_annotations-2.0.3.dist-info/RECORD
