Metadata-Version: 2.1
Name: tensor-annotations
Version: 2.0.3
Summary: Enables annotations of tensor shapes in numerical computing libraries. Includes type stubs for TensorFlow and JAX describing how library functions change shapes.
Home-page: https://github.com/deepmind/tensor_annotations
License-File: LICENSE
Requires-Dist: dm-tree
Provides-Extra: dev
Requires-Dist: absl-py ; extra == 'dev'
Requires-Dist: pytype ; extra == 'dev'
